[
	{
		"title": "Fullstack Developer in Quadra-Net",
		"description": "Development and maintenance of IT systems that I create myself, including an application for managing employee vacations in the company, a warehouse system with a used parts store, a statistical system for analyzing the results of our business partners, and a system for managing scripts automating our processes. Additionally, I am also involved in automating manual processes within the company.",
		"startDate": "October 2021",
		"endDate": "Present",
		"url": "https://quadra-net.pl"
	}
]
